[
    {
        "Book Value": 68.82,
        "Buy Units": 2,
        "Credit Dividend": 17.61,
        "Current Price": 863.35,
        "Day Returns": -2.04,
        "Debt to Equity": 0.02,
        "Dividend Yield": 2.04,
        "EPS(TTM)": 20.95,
        "Face Value": 10.0,
        "Industry P/E": 20.99,
        "Market Cap": 56106.0,
        "Name": "Nippon Life India AMC",
        "P/B Ratio": 12.8,
        "P/E Ratio(TTM)": 42.04,
        "Qty": 2,
        "ROE": 30.45,
        "Stock Average Value": 850.25,
        "Time": "2025-11-24 11:10:26",
        "To Be Credit Dividend": 35.22,
        "Total Returns": 26.200000000000045,
        "Upcoming Dividend Amount": 0,
        "Upcoming Dividend Date": "",
        "Url": "https://groww.in/stocks/reliance-nippon-life-asset-management-ltd"
    },
    {
        "Book Value": 68.82,
        "Buy Units": 1,
        "Credit Dividend": 17.42,
        "Current Price": 853.7,
        "Day Returns": -3.14,
        "Debt to Equity": 0.02,
        "Dividend Yield": 2.04,
        "EPS(TTM)": 20.95,
        "Face Value": 10.0,
        "Industry P/E": 20.99,
        "Market Cap": 56106.0,
        "Name": "Nippon Life India AMC",
        "P/B Ratio": 12.8,
        "P/E Ratio(TTM)": 42.04,
        "Qty": 2,
        "ROE": 30.45,
        "Stock Average Value": 850.25,
        "Time": "2025-11-24 12:46:13",
        "To Be Credit Dividend": 34.84,
        "Total Returns": 6.900000000000091,
        "Upcoming Dividend Amount": 0,
        "Upcoming Dividend Date": "",
        "Url": "https://groww.in/stocks/reliance-nippon-life-asset-management-ltd"
    },
    {
        "Book Value": 74.76,
        "Buy Units": 2,
        "Credit Dividend": 9.77,
        "Current Price": 213.81,
        "Day Returns": -2.17,
        "Debt to Equity": 0.11,
        "Dividend Yield": 4.57,
        "EPS(TTM)": 3.29,
        "Face Value": 10.0,
        "Industry P/E": 28.77,
        "Market Cap": 3260.0,
        "Name": "Quess Corp",
        "P/B Ratio": 2.92,
        "P/E Ratio(TTM)": 66.43,
        "Qty": 19,
        "ROE": 19.03,
        "Stock Average Value": 266.82,
        "Time": "2025-11-26 09:56:37",
        "To Be Credit Dividend": 185.63,
        "Total Returns": -1007.1899999999998,
        "Upcoming Dividend Amount": 0,
        "Upcoming Dividend Date": "",
        "Url": "https://groww.in/stocks/quess-corp-ltd"
    },
    {
        "Book Value": 1263.31,
        "Buy Units": 2,
        "Credit Dividend": 880.11,
        "Current Price": 38100.0,
        "Day Returns": -2.13,
        "Debt to Equity": 0.19,
        "Dividend Yield": 2.31,
        "EPS(TTM)": 685.16,
        "Face Value": 10.0,
        "Industry P/E": 49.88,
        "Market Cap": 43468.0,
        "Name": "Page Industries",
        "P/B Ratio": 30.85,
        "P/E Ratio(TTM)": 56.88,
        "Qty": 0,
        "ROE": 54.24,
        "Stock Average Value": 0,
        "Time": "2025-11-28 15:31:51",
        "To Be Credit Dividend": 0.0,
        "Total Returns": 0.0,
        "Upcoming Dividend Amount": 0,
        "Upcoming Dividend Date": "",
        "Url": "https://groww.in/stocks/page-industries-ltd"
    }
]