[
    {
        "Book Value": 141.83,
        "Buy Units": 2,
        "Credit Dividend": 4.65,
        "Current Price": 145.22,
        "Day Returns": -2.1,
        "Debt to Equity": 0,
        "Dividend Yield": 3.2,
        "EPS(TTM)": 23.62,
        "Face Value": 10.0,
        "Industry P/E": 13.81,
        "Market Cap": 113206.0,
        "Name": "Union Bank of India",
        "P/B Ratio": 1.05,
        "P/E Ratio(TTM)": 6.28,
        "Qty": 2,
        "ROE": 16.65,
        "Stock Average Value": 112.99,
        "Time": "2025-07-17 09:37:08",
        "To Be Credit Dividend": 9.3,
        "Total Returns": 64.46000000000001,
        "Upcoming Dividend Amount": 4.75,
        "Upcoming Dividend Date": "25 Jul, 2025",
        "Url": "https://groww.in/stocks/union-bank-of-india"
    },
    {
        "Book Value": 279.91,
        "Buy Units": 2,
        "Credit Dividend": 44.07,
        "Current Price": 1574.0,
        "Day Returns": -2.11,
        "Debt to Equity": 0.07,
        "Dividend Yield": 2.8,
        "EPS(TTM)": 43.42,
        "Face Value": 5.0,
        "Industry P/E": 27.47,
        "Market Cap": 157452.0,
        "Name": "Tech Mahindra",
        "P/B Ratio": 5.74,
        "P/E Ratio(TTM)": 37.03,
        "Qty": 11,
        "ROE": 15.54,
        "Stock Average Value": 1693.27,
        "Time": "2025-07-17 11:58:22",
        "To Be Credit Dividend": 484.77,
        "Total Returns": -1311.9699999999998,
        "Upcoming Dividend Amount": 0,
        "Upcoming Dividend Date": "",
        "Url": "https://groww.in/stocks/tech-mahindra-ltd"
    },
    {
        "Book Value": 66.32,
        "Buy Units": 2,
        "Credit Dividend": 17.63,
        "Current Price": 851.55,
        "Day Returns": -2.05,
        "Debt to Equity": 0.02,
        "Dividend Yield": 2.07,
        "EPS(TTM)": 20.25,
        "Face Value": 10.0,
        "Industry P/E": 21.91,
        "Market Cap": 55222.0,
        "Name": "Nippon Life India AMC",
        "P/B Ratio": 13.11,
        "P/E Ratio(TTM)": 42.92,
        "Qty": 5,
        "ROE": 30.53,
        "Stock Average Value": 536.65,
        "Time": "2025-07-17 13:01:35",
        "To Be Credit Dividend": 88.15,
        "Total Returns": 1574.5,
        "Upcoming Dividend Amount": 0,
        "Upcoming Dividend Date": "",
        "Url": "https://groww.in/stocks/reliance-nippon-life-asset-management-ltd"
    }
]