[
    {
        "Book Value": 104.32,
        "Buy Units": 3,
        "Credit Dividend": 3.14,
        "Current Price": 98.1,
        "Day Returns": -2.54,
        "Debt to Equity": 0,
        "Dividend Yield": 3.2,
        "EPS(TTM)": 18.1,
        "Face Value": 2.0,
        "Industry P/E": 13.47,
        "Market Cap": 91269.0,
        "Name": "Canara Bank",
        "P/B Ratio": 0.96,
        "P/E Ratio(TTM)": 5.56,
        "Qty": 38,
        "ROE": 17.35,
        "Stock Average Value": 104.23,
        "Time": "2025-04-23 10:35:33",
        "To Be Credit Dividend": 119.32,
        "Total Returns": -232.94000000000037,
        "Upcoming Dividend Amount": 0,
        "Upcoming Dividend Date": "",
        "Url": "https://groww.in/stocks/canara-bank"
    },
    {
        "Book Value": 559.74,
        "Buy Units": 2,
        "Credit Dividend": 29.32,
        "Current Price": 1315.0,
        "Day Returns": -2.12,
        "Debt to Equity": 0.03,
        "Dividend Yield": 2.23,
        "EPS(TTM)": 105.87,
        "Face Value": 10.0,
        "Industry P/E": 16.47,
        "Market Cap": 13279.0,
        "Name": "Mahanagar Gas",
        "P/B Ratio": 2.4,
        "P/E Ratio(TTM)": 12.7,
        "Qty": 8,
        "ROE": 20.65,
        "Stock Average Value": 1274.6,
        "Time": "2025-04-23 10:37:56",
        "To Be Credit Dividend": 234.56,
        "Total Returns": 323.2000000000007,
        "Upcoming Dividend Amount": 0,
        "Upcoming Dividend Date": "",
        "Url": "https://groww.in/stocks/mahanagar-gas-ltd"
    },
    {
        "Book Value": 75.48,
        "Buy Units": 2,
        "Credit Dividend": 4.41,
        "Current Price": 183.91,
        "Day Returns": -2.25,
        "Debt to Equity": 0.01,
        "Dividend Yield": 2.4,
        "EPS(TTM)": 12.12,
        "Face Value": 2.0,
        "Industry P/E": 16.47,
        "Market Cap": 26257.0,
        "Name": "Indraprastha Gas",
        "P/B Ratio": 2.48,
        "P/E Ratio(TTM)": 15.47,
        "Qty": 15,
        "ROE": 17.47,
        "Stock Average Value": 195.55,
        "Time": "2025-04-23 10:43:40",
        "To Be Credit Dividend": 66.15,
        "Total Returns": -174.60000000000022,
        "Upcoming Dividend Amount": 0,
        "Upcoming Dividend Date": "",
        "Url": "https://groww.in/stocks/indraprastha-gas-ltd"
    },
    {
        "Book Value": 32.27,
        "Buy Units": 2,
        "Credit Dividend": 2.37,
        "Current Price": 66.52,
        "Day Returns": -2.12,
        "Debt to Equity": 0.15,
        "Dividend Yield": 3.56,
        "EPS(TTM)": 7.37,
        "Face Value": 1.0,
        "Industry P/E": 10.06,
        "Market Cap": 59758.0,
        "Name": "NMDC",
        "P/B Ratio": 2.11,
        "P/E Ratio(TTM)": 9.22,
        "Qty": 209,
        "ROE": 21.43,
        "Stock Average Value": 66.32,
        "Time": "2025-04-23 10:44:59",
        "To Be Credit Dividend": 495.33,
        "Total Returns": 41.800000000000594,
        "Upcoming Dividend Amount": 0,
        "Upcoming Dividend Date": "",
        "Url": "https://groww.in/stocks/nmdc-ltd"
    },
    {
        "Book Value": 177.88,
        "Buy Units": 2,
        "Credit Dividend": 20.26,
        "Current Price": 299.75,
        "Day Returns": -2.07,
        "Debt to Equity": 0.76,
        "Dividend Yield": 6.76,
        "EPS(TTM)": 31.66,
        "Face Value": 10.0,
        "Industry P/E": 22.12,
        "Market Cap": 132823.0,
        "Name": "Bharat Petroleum Corporation",
        "P/B Ratio": 1.72,
        "P/E Ratio(TTM)": 9.67,
        "Qty": 2,
        "ROE": 17.0,
        "Stock Average Value": 253.4,
        "Time": "2025-04-23 10:52:23",
        "To Be Credit Dividend": 40.52,
        "Total Returns": 92.69999999999999,
        "Upcoming Dividend Amount": 0,
        "Upcoming Dividend Date": "",
        "Url": "https://groww.in/stocks/bharat-petroleum-corporation-ltd"
    },
    {
        "Book Value": 139.52,
        "Buy Units": 2,
        "Credit Dividend": 3.53,
        "Current Price": 125.3,
        "Day Returns": -2.06,
        "Debt to Equity": 0,
        "Dividend Yield": 2.82,
        "EPS(TTM)": 21.41,
        "Face Value": 10.0,
        "Industry P/E": 13.47,
        "Market Cap": 97405.0,
        "Name": "Union Bank of India",
        "P/B Ratio": 0.91,
        "P/E Ratio(TTM)": 5.96,
        "Qty": 27,
        "ROE": 15.35,
        "Stock Average Value": 122.18,
        "Time": "2025-04-23 11:27:06",
        "To Be Credit Dividend": 95.31,
        "Total Returns": 84.23999999999974,
        "Upcoming Dividend Amount": 0,
        "Upcoming Dividend Date": "",
        "Url": "https://groww.in/stocks/union-bank-of-india"
    }
]