[
    {
        "Book Value": 231.04,
        "Credit Dividend": 0.0,
        "Current Price": 288.8,
        "Day Returns": 1.28,
        "Debt to Equity": 0.54,
        "Dividend Yield": 0.0,
        "EPS(TTM)": 59.57,
        "Face Value": 10.0,
        "Industry P/E": 13.34,
        "Market Cap": 123669.0,
        "Name": "Bharat Petroleum Corporation",
        "P/B Ratio": 1.23,
        "P/E Ratio(TTM)": 4.79,
        "Qty": 42,
        "ROE": 25.8,
        "Stock Average Value": 322.97,
        "Time": "2026-06-09 15:29:41",
        "To Be Credit Dividend": 0.0,
        "Total Returns": -1435.1400000000008,
        "Upcoming Dividend Amount": 0,
        "Upcoming Dividend Date": "",
        "Url": "https://groww.in/stocks/bharat-petroleum-corporation-ltd"
    },
    {
        "Book Value": 122.68,
        "Credit Dividend": 4.4,
        "Current Price": 137.8,
        "Day Returns": 4.47,
        "Debt to Equity": 0,
        "Dividend Yield": 3.19,
        "EPS(TTM)": 21.73,
        "Face Value": 2.0,
        "Industry P/E": 12.49,
        "Market Cap": 119597.0,
        "Name": "Canara Bank",
        "P/B Ratio": 1.07,
        "P/E Ratio(TTM)": 6.07,
        "Qty": 46,
        "ROE": 17.71,
        "Stock Average Value": 105.98,
        "Time": "2026-06-09 15:29:48",
        "To Be Credit Dividend": 202.4,
        "Total Returns": 1463.7200000000003,
        "Upcoming Dividend Amount": 4.2,
        "Upcoming Dividend Date": "12 Jun, 2026",
        "Url": "https://groww.in/stocks/canara-bank"
    },
    {
        "Book Value": 19.21,
        "Credit Dividend": 13.22,
        "Current Price": 182.53,
        "Day Returns": -0.29,
        "Debt to Equity": 0.03,
        "Dividend Yield": 7.24,
        "EPS(TTM)": 9.69,
        "Face Value": 5.0,
        "Industry P/E": 41.83,
        "Market Cap": 18106.0,
        "Name": "Castrol India",
        "P/B Ratio": 9.53,
        "P/E Ratio(TTM)": 18.89,
        "Qty": 86,
        "ROE": 49.99,
        "Stock Average Value": 215.91,
        "Time": "2026-06-09 15:29:55",
        "To Be Credit Dividend": 1136.92,
        "Total Returns": -2870.6799999999994,
        "Upcoming Dividend Amount": 0,
        "Upcoming Dividend Date": "",
        "Url": "https://groww.in/stocks/castrol-india-ltd"
    },
    {
        "Book Value": 193.26,
        "Credit Dividend": 26.8,
        "Current Price": 466.1,
        "Day Returns": 0.26,
        "Debt to Equity": 0.12,
        "Dividend Yield": 5.75,
        "EPS(TTM)": 50.42,
        "Face Value": 10.0,
        "Industry P/E": 11.66,
        "Market Cap": 286721.0,
        "Name": "Coal India",
        "P/B Ratio": 2.41,
        "P/E Ratio(TTM)": 9.23,
        "Qty": 50,
        "ROE": 26.11,
        "Stock Average Value": 374.23,
        "Time": "2026-06-09 15:30:02",
        "To Be Credit Dividend": 1340.0,
        "Total Returns": 4593.5,
        "Upcoming Dividend Amount": 0,
        "Upcoming Dividend Date": "",
        "Url": "https://groww.in/stocks/coal-india-ltd"
    },
    {
        "Book Value": 58.24,
        "Credit Dividend": 48.32,
        "Current Price": 2021.8,
        "Day Returns": 0.81,
        "Debt to Equity": 0.03,
        "Dividend Yield": 2.39,
        "EPS(TTM)": 48.73,
        "Face Value": 1.0,
        "Industry P/E": 47.97,
        "Market Cap": 54602.0,
        "Name": "Colgate-Palmolive (India)",
        "P/B Ratio": 34.47,
        "P/E Ratio(TTM)": 41.2,
        "Qty": 14,
        "ROE": 83.66,
        "Stock Average Value": 2091.52,
        "Time": "2026-06-09 15:30:08",
        "To Be Credit Dividend": 676.48,
        "Total Returns": -976.0800000000004,
        "Upcoming Dividend Amount": 0,
        "Upcoming Dividend Date": "",
        "Url": "https://groww.in/stocks/colgatepalmolive-india-ltd"
    },
    {
        "Book Value": 401.74,
        "Credit Dividend": 10.09,
        "Current Price": 388.0,
        "Day Returns": 0.79,
        "Debt to Equity": 0.0,
        "Dividend Yield": 2.6,
        "EPS(TTM)": 55.08,
        "Face Value": 5.0,
        "Industry P/E": 11.02,
        "Market Cap": 67518.0,
        "Name": "General Insurance Corporation of India",
        "P/B Ratio": 0.96,
        "P/E Ratio(TTM)": 6.99,
        "Qty": 51,
        "ROE": 13.71,
        "Stock Average Value": 405.37,
        "Time": "2026-06-09 15:30:14",
        "To Be Credit Dividend": 514.59,
        "Total Returns": -885.8700000000002,
        "Upcoming Dividend Amount": 0,
        "Upcoming Dividend Date": "",
        "Url": "https://groww.in/stocks/general-insurance-corporation-of-india-ltd"
    },
    {
        "Book Value": 276.99,
        "Credit Dividend": 53.97,
        "Current Price": 1148.3,
        "Day Returns": -0.26,
        "Debt to Equity": 0.07,
        "Dividend Yield": 4.7,
        "EPS(TTM)": 61.36,
        "Face Value": 2.0,
        "Industry P/E": 19.05,
        "Market Cap": 312207.0,
        "Name": "HCL Technologies",
        "P/B Ratio": 4.15,
        "P/E Ratio(TTM)": 18.75,
        "Qty": 30,
        "ROE": 22.14,
        "Stock Average Value": 1415.98,
        "Time": "2026-06-09 15:30:21",
        "To Be Credit Dividend": 1619.1,
        "Total Returns": -8030.4000000000015,
        "Upcoming Dividend Amount": 0,
        "Upcoming Dividend Date": "",
        "Url": "https://groww.in/stocks/hcl-technologies-ltd"
    },
    {
        "Book Value": 1080.06,
        "Credit Dividend": 187.69,
        "Current Price": 4850.0,
        "Day Returns": 1.56,
        "Debt to Equity": 0.04,
        "Dividend Yield": 3.87,
        "EPS(TTM)": 288.65,
        "Face Value": 2.0,
        "Industry P/E": 23.76,
        "Market Cap": 95571.0,
        "Name": "Hero MotoCorp",
        "P/B Ratio": 4.42,
        "P/E Ratio(TTM)": 16.55,
        "Qty": 38,
        "ROE": 26.57,
        "Stock Average Value": 4096.87,
        "Time": "2026-06-09 15:30:26",
        "To Be Credit Dividend": 7132.22,
        "Total Returns": 28618.940000000002,
        "Upcoming Dividend Amount": 75.0,
        "Upcoming Dividend Date": "24 Jul, 2026",
        "Url": "https://groww.in/stocks/hero-motocorp-ltd"
    },
    {
        "Book Value": 53.56,
        "Credit Dividend": 10.17,
        "Current Price": 564.8,
        "Day Returns": 1.58,
        "Debt to Equity": 0.39,
        "Dividend Yield": 1.8,
        "EPS(TTM)": 32.74,
        "Face Value": 2.0,
        "Industry P/E": 16.88,
        "Market Cap": 234864.0,
        "Name": "Hindustan Zinc",
        "P/B Ratio": 10.38,
        "P/E Ratio(TTM)": 16.98,
        "Qty": 57,
        "ROE": 61.13,
        "Stock Average Value": 505.27,
        "Time": "2026-06-09 15:30:33",
        "To Be Credit Dividend": 579.69,
        "Total Returns": 3393.209999999998,
        "Upcoming Dividend Amount": 0,
        "Upcoming Dividend Date": "",
        "Url": "https://groww.in/stocks/hindustan-zinc-ltd"
    },
    {
        "Book Value": 216.98,
        "Credit Dividend": 47.74,
        "Current Price": 1181.7,
        "Day Returns": -0.5,
        "Debt to Equity": 0.1,
        "Dividend Yield": 4.04,
        "EPS(TTM)": 72.65,
        "Face Value": 5.0,
        "Industry P/E": 19.05,
        "Market Cap": 481698.0,
        "Name": "Infosys",
        "P/B Ratio": 5.47,
        "P/E Ratio(TTM)": 16.34,
        "Qty": 73,
        "ROE": 31.71,
        "Stock Average Value": 1415.89,
        "Time": "2026-06-09 15:30:38",
        "To Be Credit Dividend": 3485.02,
        "Total Returns": -17095.870000000003,
        "Upcoming Dividend Amount": 25.0,
        "Upcoming Dividend Date": "10 Jun, 2026",
        "Url": "https://groww.in/stocks/infosys-ltd"
    },
    {
        "Book Value": 57.87,
        "Credit Dividend": 14.53,
        "Current Price": 280.0,
        "Day Returns": 0.2,
        "Debt to Equity": 0.03,
        "Dividend Yield": 5.19,
        "EPS(TTM)": 16.77,
        "Face Value": 1.0,
        "Industry P/E": 17.19,
        "Market Cap": 350073.0,
        "Name": "ITC",
        "P/B Ratio": 4.83,
        "P/E Ratio(TTM)": 16.66,
        "Qty": 141,
        "ROE": 28.53,
        "Stock Average Value": 345.01,
        "Time": "2026-06-09 15:30:44",
        "To Be Credit Dividend": 2048.73,
        "Total Returns": -9166.409999999998,
        "Upcoming Dividend Amount": 0,
        "Upcoming Dividend Date": "",
        "Url": "https://groww.in/stocks/itc-ltd"
    },
    {
        "Book Value": 117.63,
        "Credit Dividend": 10.7,
        "Current Price": 385.0,
        "Day Returns": 1.8,
        "Debt to Equity": 0.0,
        "Dividend Yield": 2.78,
        "EPS(TTM)": 31.56,
        "Face Value": 5.0,
        "Industry P/E": 16.88,
        "Market Cap": 69406.0,
        "Name": "National Aluminium Co",
        "P/B Ratio": 3.21,
        "P/E Ratio(TTM)": 11.97,
        "Qty": 49,
        "ROE": 26.83,
        "Stock Average Value": 178.62,
        "Time": "2026-06-09 15:30:50",
        "To Be Credit Dividend": 524.3,
        "Total Returns": 10112.619999999999,
        "Upcoming Dividend Amount": 0,
        "Upcoming Dividend Date": "",
        "Url": "https://groww.in/stocks/national-aluminium-company-ltd"
    },
    {
        "Book Value": 38.74,
        "Credit Dividend": 3.51,
        "Current Price": 90.09,
        "Day Returns": 0.56,
        "Debt to Equity": 0.19,
        "Dividend Yield": 3.9,
        "EPS(TTM)": 8.47,
        "Face Value": 1.0,
        "Industry P/E": 11.66,
        "Market Cap": 78801.0,
        "Name": "NMDC",
        "P/B Ratio": 2.31,
        "P/E Ratio(TTM)": 10.58,
        "Qty": 226,
        "ROE": 21.87,
        "Stock Average Value": 66.5,
        "Time": "2026-06-09 15:30:56",
        "To Be Credit Dividend": 793.26,
        "Total Returns": 5331.340000000001,
        "Upcoming Dividend Amount": 0,
        "Upcoming Dividend Date": "",
        "Url": "https://groww.in/stocks/nmdc-ltd"
    },
    {
        "Book Value": 898.94,
        "Credit Dividend": 267.61,
        "Current Price": 9661.0,
        "Day Returns": -0.97,
        "Debt to Equity": 0.0,
        "Dividend Yield": 2.77,
        "EPS(TTM)": 303.14,
        "Face Value": 5.0,
        "Industry P/E": 19.05,
        "Market Cap": 84857.0,
        "Name": "Oracle Financial Services Software",
        "P/B Ratio": 10.84,
        "P/E Ratio(TTM)": 32.15,
        "Qty": 5,
        "ROE": 33.72,
        "Stock Average Value": 7614.66,
        "Time": "2026-06-09 15:31:02",
        "To Be Credit Dividend": 1338.05,
        "Total Returns": 10231.7,
        "Upcoming Dividend Amount": 0,
        "Upcoming Dividend Date": "",
        "Url": "https://groww.in/stocks/oracle-financial-services-software-ltd"
    },
    {
        "Book Value": 148.57,
        "Credit Dividend": 3.01,
        "Current Price": 268.4,
        "Day Returns": 0.39,
        "Debt to Equity": 0.11,
        "Dividend Yield": 1.12,
        "EPS(TTM)": 26.08,
        "Face Value": 10.0,
        "Industry P/E": 18.63,
        "Market Cap": 40095.0,
        "Name": "Petronet LNG",
        "P/B Ratio": 1.8,
        "P/E Ratio(TTM)": 10.25,
        "Qty": 27,
        "ROE": 17.56,
        "Stock Average Value": 295.9,
        "Time": "2026-06-09 15:31:09",
        "To Be Credit Dividend": 81.27,
        "Total Returns": -742.5,
        "Upcoming Dividend Amount": 3.0,
        "Upcoming Dividend Date": "12 Jun, 2026",
        "Url": "https://groww.in/stocks/petronet-lng-ltd"
    },
    {
        "Book Value": 918.71,
        "Credit Dividend": 75.96,
        "Current Price": 4576.0,
        "Day Returns": 1.06,
        "Debt to Equity": 0.02,
        "Dividend Yield": 1.66,
        "EPS(TTM)": 157.92,
        "Face Value": 10.0,
        "Industry P/E": 44.77,
        "Market Cap": 20729.0,
        "Name": "Pfizer",
        "P/B Ratio": 4.93,
        "P/E Ratio(TTM)": 28.69,
        "Qty": 9,
        "ROE": 17.19,
        "Stock Average Value": 5292.38,
        "Time": "2026-06-09 15:31:14",
        "To Be Credit Dividend": 683.64,
        "Total Returns": -6447.420000000001,
        "Upcoming Dividend Amount": 75.0,
        "Upcoming Dividend Date": "17 Jul, 2026",
        "Url": "https://groww.in/stocks/pfizer-ltd"
    },
    {
        "Book Value": 78.11,
        "Credit Dividend": 11.0,
        "Current Price": 236.05,
        "Day Returns": -0.0,
        "Debt to Equity": 0.11,
        "Dividend Yield": 4.66,
        "EPS(TTM)": 14.88,
        "Face Value": 10.0,
        "Industry P/E": 24.57,
        "Market Cap": 3525.0,
        "Name": "Quess Corp",
        "P/B Ratio": 3.02,
        "P/E Ratio(TTM)": 15.86,
        "Qty": 70,
        "ROE": 19.0,
        "Stock Average Value": 208.49,
        "Time": "2026-06-09 15:31:21",
        "To Be Credit Dividend": 770.0,
        "Total Returns": 1929.2000000000003,
        "Upcoming Dividend Amount": 0,
        "Upcoming Dividend Date": "",
        "Url": "https://groww.in/stocks/quess-corp-ltd"
    },
    {
        "Book Value": 234.07,
        "Credit Dividend": 110.18,
        "Current Price": 2152.0,
        "Day Returns": 0.03,
        "Debt to Equity": 0.11,
        "Dividend Yield": 5.12,
        "EPS(TTM)": 135.7,
        "Face Value": 1.0,
        "Industry P/E": 21.2,
        "Market Cap": 778413.0,
        "Name": "Tata Consultancy Services",
        "P/B Ratio": 9.19,
        "P/E Ratio(TTM)": 15.85,
        "Qty": 25,
        "ROE": 57.98,
        "Stock Average Value": 2708.87,
        "Time": "2026-06-09 15:31:26",
        "To Be Credit Dividend": 2754.5,
        "Total Returns": -13921.749999999996,
        "Upcoming Dividend Amount": 0,
        "Upcoming Dividend Date": "",
        "Url": "https://groww.in/stocks/tata-consultancy-services-ltd"
    },
    {
        "Book Value": 302.69,
        "Credit Dividend": 45.64,
        "Current Price": 1486.5,
        "Day Returns": -1.12,
        "Debt to Equity": 0.07,
        "Dividend Yield": 3.07,
        "EPS(TTM)": 49.04,
        "Face Value": 5.0,
        "Industry P/E": 19.05,
        "Market Cap": 147263.0,
        "Name": "Tech Mahindra",
        "P/B Ratio": 4.96,
        "P/E Ratio(TTM)": 30.64,
        "Qty": 13,
        "ROE": 16.24,
        "Stock Average Value": 1638.45,
        "Time": "2026-06-09 15:31:33",
        "To Be Credit Dividend": 593.32,
        "Total Returns": -1975.3500000000006,
        "Upcoming Dividend Amount": 36.0,
        "Upcoming Dividend Date": "03 Jul, 2026",
        "Url": "https://groww.in/stocks/tech-mahindra-ltd"
    },
    {
        "Book Value": 167.66,
        "Credit Dividend": 5.14,
        "Current Price": 170.28,
        "Day Returns": 3.09,
        "Debt to Equity": 0,
        "Dividend Yield": 3.02,
        "EPS(TTM)": 25.45,
        "Face Value": 10.0,
        "Industry P/E": 12.49,
        "Market Cap": 126184.0,
        "Name": "Union Bank of India",
        "P/B Ratio": 0.99,
        "P/E Ratio(TTM)": 6.5,
        "Qty": 40,
        "ROE": 15.18,
        "Stock Average Value": 127.89,
        "Time": "2026-06-09 15:31:38",
        "To Be Credit Dividend": 205.6,
        "Total Returns": 1695.6,
        "Upcoming Dividend Amount": 5.0,
        "Upcoming Dividend Date": "03 Jul, 2026",
        "Url": "https://groww.in/stocks/union-bank-of-india"
    },
    {
        "Book Value": 83.85,
        "Credit Dividend": 11.0,
        "Current Price": 181.9,
        "Day Returns": 0.08,
        "Debt to Equity": 0.23,
        "Dividend Yield": 6.05,
        "EPS(TTM)": 12.64,
        "Face Value": 2.0,
        "Industry P/E": 19.05,
        "Market Cap": 190836.0,
        "Name": "Wipro",
        "P/B Ratio": 2.17,
        "P/E Ratio(TTM)": 14.38,
        "Qty": 42,
        "ROE": 14.99,
        "Stock Average Value": 233.42,
        "Time": "2026-06-09 15:31:43",
        "To Be Credit Dividend": 462.0,
        "Total Returns": -2163.8399999999992,
        "Upcoming Dividend Amount": 0,
        "Upcoming Dividend Date": "",
        "Url": "https://groww.in/stocks/wipro-ltd"
    },
    {
        "Book Value": 231.04,
        "Credit Dividend": 0.0,
        "Current Price": 288.9,
        "Day Returns": 1.32,
        "Debt to Equity": 0.54,
        "Dividend Yield": 0.0,
        "EPS(TTM)": 59.57,
        "Face Value": 10.0,
        "Industry P/E": 13.34,
        "Market Cap": 123669.0,
        "Name": "Bharat Petroleum Corporation",
        "P/B Ratio": 1.23,
        "P/E Ratio(TTM)": 4.79,
        "Qty": 13,
        "ROE": 25.8,
        "Stock Average Value": 331.32,
        "Time": "2026-06-09 15:31:50",
        "To Be Credit Dividend": 0.0,
        "Total Returns": -551.4600000000003,
        "Upcoming Dividend Amount": 0,
        "Upcoming Dividend Date": "",
        "Url": "https://groww.in/stocks/bharat-petroleum-corporation-ltd"
    },
    {
        "Book Value": 150.28,
        "Credit Dividend": 13.76,
        "Current Price": 419.6,
        "Day Returns": -1.54,
        "Debt to Equity": 0.53,
        "Dividend Yield": 3.28,
        "EPS(TTM)": 27.08,
        "Face Value": 10.0,
        "Industry P/E": 18.95,
        "Market Cap": 112465.0,
        "Name": "Indus Towers",
        "P/B Ratio": 2.84,
        "P/E Ratio(TTM)": 15.74,
        "Qty": 0,
        "ROE": 18.02,
        "Stock Average Value": 0,
        "Time": "2026-06-09 15:31:56",
        "To Be Credit Dividend": 0.0,
        "Total Returns": 0.0,
        "Upcoming Dividend Amount": 0,
        "Upcoming Dividend Date": "",
        "Url": "https://groww.in/stocks/bharti-infratel-ltd"
    },
    {
        "Book Value": 122.68,
        "Credit Dividend": 4.4,
        "Current Price": 137.8,
        "Day Returns": 4.47,
        "Debt to Equity": 0,
        "Dividend Yield": 3.19,
        "EPS(TTM)": 21.73,
        "Face Value": 2.0,
        "Industry P/E": 12.49,
        "Market Cap": 119597.0,
        "Name": "Canara Bank",
        "P/B Ratio": 1.07,
        "P/E Ratio(TTM)": 6.07,
        "Qty": 29,
        "ROE": 17.71,
        "Stock Average Value": 132.17,
        "Time": "2026-06-09 15:32:03",
        "To Be Credit Dividend": 127.6,
        "Total Returns": 163.2700000000007,
        "Upcoming Dividend Amount": 4.2,
        "Upcoming Dividend Date": "12 Jun, 2026",
        "Url": "https://groww.in/stocks/canara-bank"
    },
    {
        "Book Value": 19.21,
        "Credit Dividend": 13.21,
        "Current Price": 182.51,
        "Day Returns": -0.3,
        "Debt to Equity": 0.03,
        "Dividend Yield": 7.24,
        "EPS(TTM)": 9.69,
        "Face Value": 5.0,
        "Industry P/E": 41.83,
        "Market Cap": 18106.0,
        "Name": "Castrol India",
        "P/B Ratio": 9.53,
        "P/E Ratio(TTM)": 18.89,
        "Qty": 7,
        "ROE": 49.99,
        "Stock Average Value": 202.81,
        "Time": "2026-06-09 15:32:10",
        "To Be Credit Dividend": 92.47,
        "Total Returns": -142.10000000000008,
        "Upcoming Dividend Amount": 0,
        "Upcoming Dividend Date": "",
        "Url": "https://groww.in/stocks/castrol-india-ltd"
    },
    {
        "Book Value": 193.26,
        "Credit Dividend": 26.8,
        "Current Price": 466.15,
        "Day Returns": 0.27,
        "Debt to Equity": 0.12,
        "Dividend Yield": 5.75,
        "EPS(TTM)": 50.42,
        "Face Value": 10.0,
        "Industry P/E": 11.66,
        "Market Cap": 286721.0,
        "Name": "Coal India",
        "P/B Ratio": 2.41,
        "P/E Ratio(TTM)": 9.23,
        "Qty": 6,
        "ROE": 26.11,
        "Stock Average Value": 384.52,
        "Time": "2026-06-09 15:32:16",
        "To Be Credit Dividend": 160.8,
        "Total Returns": 489.78,
        "Upcoming Dividend Amount": 0,
        "Upcoming Dividend Date": "",
        "Url": "https://groww.in/stocks/coal-india-ltd"
    },
    {
        "Book Value": 58.24,
        "Credit Dividend": 48.32,
        "Current Price": 2021.9,
        "Day Returns": 0.82,
        "Debt to Equity": 0.03,
        "Dividend Yield": 2.39,
        "EPS(TTM)": 48.73,
        "Face Value": 1.0,
        "Industry P/E": 47.97,
        "Market Cap": 54602.0,
        "Name": "Colgate-Palmolive (India)",
        "P/B Ratio": 34.47,
        "P/E Ratio(TTM)": 41.2,
        "Qty": 7,
        "ROE": 83.66,
        "Stock Average Value": 2180.44,
        "Time": "2026-06-09 15:32:21",
        "To Be Credit Dividend": 338.24,
        "Total Returns": -1109.7799999999997,
        "Upcoming Dividend Amount": 0,
        "Upcoming Dividend Date": "",
        "Url": "https://groww.in/stocks/colgatepalmolive-india-ltd"
    },
    {
        "Book Value": 66.99,
        "Credit Dividend": 6.13,
        "Current Price": 393.0,
        "Day Returns": 2.08,
        "Debt to Equity": 0.06,
        "Dividend Yield": 1.56,
        "EPS(TTM)": 17.76,
        "Face Value": 1.0,
        "Industry P/E": 46.15,
        "Market Cap": 16810.0,
        "Name": "Emami",
        "P/B Ratio": 5.75,
        "P/E Ratio(TTM)": 21.68,
        "Qty": 5,
        "ROE": 26.51,
        "Stock Average Value": 459.22,
        "Time": "2026-06-09 15:32:28",
        "To Be Credit Dividend": 30.65,
        "Total Returns": -331.10000000000014,
        "Upcoming Dividend Amount": 0,
        "Upcoming Dividend Date": "",
        "Url": "https://groww.in/stocks/emami-ltd"
    },
    {
        "Book Value": 276.99,
        "Credit Dividend": 53.97,
        "Current Price": 1148.3,
        "Day Returns": -0.26,
        "Debt to Equity": 0.07,
        "Dividend Yield": 4.7,
        "EPS(TTM)": 61.36,
        "Face Value": 2.0,
        "Industry P/E": 19.05,
        "Market Cap": 312207.0,
        "Name": "HCL Technologies",
        "P/B Ratio": 4.15,
        "P/E Ratio(TTM)": 18.75,
        "Qty": 10,
        "ROE": 22.14,
        "Stock Average Value": 1377.24,
        "Time": "2026-06-09 15:32:34",
        "To Be Credit Dividend": 539.7,
        "Total Returns": -2289.4000000000005,
        "Upcoming Dividend Amount": 0,
        "Upcoming Dividend Date": "",
        "Url": "https://groww.in/stocks/hcl-technologies-ltd"
    },
    {
        "Book Value": 215.3,
        "Credit Dividend": 55.06,
        "Current Price": 2502.8,
        "Day Returns": 2.03,
        "Debt to Equity": 0.0,
        "Dividend Yield": 2.2,
        "EPS(TTM)": 66.68,
        "Face Value": 5.0,
        "Industry P/E": 18.28,
        "Market Cap": 104975.0,
        "Name": "HDFC Asset Management Company",
        "P/B Ratio": 11.37,
        "P/E Ratio(TTM)": 36.73,
        "Qty": 3,
        "ROE": 30.97,
        "Stock Average Value": 2507.2,
        "Time": "2026-06-09 15:32:40",
        "To Be Credit Dividend": 165.18,
        "Total Returns": -13.199999999998909,
        "Upcoming Dividend Amount": 0,
        "Upcoming Dividend Date": "",
        "Url": "https://groww.in/stocks/hdfc-asset-management-company-ltd"
    },
    {
        "Book Value": 1080.06,
        "Credit Dividend": 187.69,
        "Current Price": 4850.0,
        "Day Returns": 1.56,
        "Debt to Equity": 0.04,
        "Dividend Yield": 3.87,
        "EPS(TTM)": 288.65,
        "Face Value": 2.0,
        "Industry P/E": 23.76,
        "Market Cap": 95571.0,
        "Name": "Hero MotoCorp",
        "P/B Ratio": 4.42,
        "P/E Ratio(TTM)": 16.55,
        "Qty": 11,
        "ROE": 26.57,
        "Stock Average Value": 5550.04,
        "Time": "2026-06-09 15:32:46",
        "To Be Credit Dividend": 2064.59,
        "Total Returns": -7700.44,
        "Upcoming Dividend Amount": 75.0,
        "Upcoming Dividend Date": "24 Jul, 2026",
        "Url": "https://groww.in/stocks/hero-motocorp-ltd"
    },
    {
        "Book Value": 308.09,
        "Credit Dividend": 24.87,
        "Current Price": 382.65,
        "Day Returns": 2.66,
        "Debt to Equity": 0.85,
        "Dividend Yield": 6.5,
        "EPS(TTM)": 84.81,
        "Face Value": 10.0,
        "Industry P/E": 13.34,
        "Market Cap": 79336.0,
        "Name": "Hindustan Petroleum Corporation",
        "P/B Ratio": 1.21,
        "P/E Ratio(TTM)": 4.4,
        "Qty": 0,
        "ROE": 27.53,
        "Stock Average Value": 0,
        "Time": "2026-06-09 15:32:52",
        "To Be Credit Dividend": 0.0,
        "Total Returns": 0.0,
        "Upcoming Dividend Amount": 0,
        "Upcoming Dividend Date": "",
        "Url": "https://groww.in/stocks/hindustan-petroleum-corporation-ltd"
    },
    {
        "Book Value": 207.44,
        "Credit Dividend": 41.42,
        "Current Price": 2134.9,
        "Day Returns": 1.18,
        "Debt to Equity": 0.03,
        "Dividend Yield": 1.94,
        "EPS(TTM)": 64.09,
        "Face Value": 1.0,
        "Industry P/E": 46.15,
        "Market Cap": 495576.0,
        "Name": "Hindustan Unilever",
        "P/B Ratio": 10.17,
        "P/E Ratio(TTM)": 32.91,
        "Qty": 10,
        "ROE": 22.41,
        "Stock Average Value": 2366.82,
        "Time": "2026-06-09 15:32:58",
        "To Be Credit Dividend": 414.2,
        "Total Returns": -2319.2000000000007,
        "Upcoming Dividend Amount": 22.0,
        "Upcoming Dividend Date": "23 Jun, 2026",
        "Url": "https://groww.in/stocks/hindustan-unilever-ltd"
    },
    {
        "Book Value": 53.56,
        "Credit Dividend": 10.17,
        "Current Price": 564.8,
        "Day Returns": 1.58,
        "Debt to Equity": 0.39,
        "Dividend Yield": 1.8,
        "EPS(TTM)": 32.74,
        "Face Value": 2.0,
        "Industry P/E": 16.88,
        "Market Cap": 234864.0,
        "Name": "Hindustan Zinc",
        "P/B Ratio": 10.38,
        "P/E Ratio(TTM)": 16.98,
        "Qty": 24,
        "ROE": 61.13,
        "Stock Average Value": 552.96,
        "Time": "2026-06-09 15:33:05",
        "To Be Credit Dividend": 244.08,
        "Total Returns": 284.15999999999804,
        "Upcoming Dividend Amount": 0,
        "Upcoming Dividend Date": "",
        "Url": "https://groww.in/stocks/hindustan-zinc-ltd"
    },
    {
        "Book Value": 57.87,
        "Credit Dividend": 14.53,
        "Current Price": 280.0,
        "Day Returns": 0.2,
        "Debt to Equity": 0.03,
        "Dividend Yield": 5.19,
        "EPS(TTM)": 16.77,
        "Face Value": 1.0,
        "Industry P/E": 17.19,
        "Market Cap": 350073.0,
        "Name": "ITC",
        "P/B Ratio": 4.83,
        "P/E Ratio(TTM)": 16.66,
        "Qty": 45,
        "ROE": 28.53,
        "Stock Average Value": 342.26,
        "Time": "2026-06-09 15:33:11",
        "To Be Credit Dividend": 653.85,
        "Total Returns": -2801.7,
        "Upcoming Dividend Amount": 0,
        "Upcoming Dividend Date": "",
        "Url": "https://groww.in/stocks/itc-ltd"
    },
    {
        "Book Value": 216.98,
        "Credit Dividend": 47.74,
        "Current Price": 1181.7,
        "Day Returns": -0.5,
        "Debt to Equity": 0.1,
        "Dividend Yield": 4.04,
        "EPS(TTM)": 72.65,
        "Face Value": 5.0,
        "Industry P/E": 19.05,
        "Market Cap": 481698.0,
        "Name": "Infosys",
        "P/B Ratio": 5.47,
        "P/E Ratio(TTM)": 16.34,
        "Qty": 13,
        "ROE": 31.71,
        "Stock Average Value": 1276.4,
        "Time": "2026-06-09 15:33:18",
        "To Be Credit Dividend": 620.62,
        "Total Returns": -1231.1000000000006,
        "Upcoming Dividend Amount": 25.0,
        "Upcoming Dividend Date": "10 Jun, 2026",
        "Url": "https://groww.in/stocks/infosys-ltd"
    },
    {
        "Book Value": 650.71,
        "Credit Dividend": 0.0,
        "Current Price": 1060.5,
        "Day Returns": -0.86,
        "Debt to Equity": 0.03,
        "Dividend Yield": 0.0,
        "EPS(TTM)": 85.1,
        "Face Value": 10.0,
        "Industry P/E": 18.63,
        "Market Cap": 10572.0,
        "Name": "Mahanagar Gas",
        "P/B Ratio": 1.64,
        "P/E Ratio(TTM)": 12.58,
        "Qty": 16,
        "ROE": 13.09,
        "Stock Average Value": 1072.93,
        "Time": "2026-06-09 15:33:23",
        "To Be Credit Dividend": 0.0,
        "Total Returns": -198.88000000000102,
        "Upcoming Dividend Amount": 0,
        "Upcoming Dividend Date": "",
        "Url": "https://groww.in/stocks/mahanagar-gas-ltd"
    },
    {
        "Book Value": 562.92,
        "Credit Dividend": 62.14,
        "Current Price": 2336.0,
        "Day Returns": 0.08,
        "Debt to Equity": 0.24,
        "Dividend Yield": 2.66,
        "EPS(TTM)": 97.59,
        "Face Value": 10.0,
        "Industry P/E": 19.05,
        "Market Cap": 44546.0,
        "Name": "Mphasis",
        "P/B Ratio": 4.15,
        "P/E Ratio(TTM)": 23.92,
        "Qty": 3,
        "ROE": 17.34,
        "Stock Average Value": 2383.6,
        "Time": "2026-06-09 15:33:30",
        "To Be Credit Dividend": 186.42,
        "Total Returns": -142.79999999999973,
        "Upcoming Dividend Amount": 62.0,
        "Upcoming Dividend Date": "08 Jul, 2026",
        "Url": "https://groww.in/stocks/mphasis-ltd"
    },
    {
        "Book Value": 117.63,
        "Credit Dividend": 10.7,
        "Current Price": 385.0,
        "Day Returns": 1.8,
        "Debt to Equity": 0.0,
        "Dividend Yield": 2.78,
        "EPS(TTM)": 31.56,
        "Face Value": 5.0,
        "Industry P/E": 16.88,
        "Market Cap": 69406.0,
        "Name": "National Aluminium Co",
        "P/B Ratio": 3.21,
        "P/E Ratio(TTM)": 11.97,
        "Qty": 40,
        "ROE": 26.83,
        "Stock Average Value": 343.73,
        "Time": "2026-06-09 15:33:36",
        "To Be Credit Dividend": 428.0,
        "Total Returns": 1650.7999999999993,
        "Upcoming Dividend Amount": 0,
        "Upcoming Dividend Date": "",
        "Url": "https://groww.in/stocks/national-aluminium-company-ltd"
    },
    {
        "Book Value": 38.74,
        "Credit Dividend": 3.51,
        "Current Price": 90.09,
        "Day Returns": 0.56,
        "Debt to Equity": 0.19,
        "Dividend Yield": 3.9,
        "EPS(TTM)": 8.47,
        "Face Value": 1.0,
        "Industry P/E": 11.66,
        "Market Cap": 78801.0,
        "Name": "NMDC",
        "P/B Ratio": 2.31,
        "P/E Ratio(TTM)": 10.58,
        "Qty": 29,
        "ROE": 21.87,
        "Stock Average Value": 76.44,
        "Time": "2026-06-09 15:33:41",
        "To Be Credit Dividend": 101.79,
        "Total Returns": 395.85000000000014,
        "Upcoming Dividend Amount": 0,
        "Upcoming Dividend Date": "",
        "Url": "https://groww.in/stocks/nmdc-ltd"
    },
    {
        "Book Value": 898.94,
        "Credit Dividend": 267.61,
        "Current Price": 9661.0,
        "Day Returns": -0.97,
        "Debt to Equity": 0.0,
        "Dividend Yield": 2.77,
        "EPS(TTM)": 303.14,
        "Face Value": 5.0,
        "Industry P/E": 19.05,
        "Market Cap": 84857.0,
        "Name": "Oracle Financial Services Software",
        "P/B Ratio": 10.84,
        "P/E Ratio(TTM)": 32.15,
        "Qty": 7,
        "ROE": 33.72,
        "Stock Average Value": 7779.34,
        "Time": "2026-06-09 15:33:47",
        "To Be Credit Dividend": 1873.27,
        "Total Returns": 13171.619999999999,
        "Upcoming Dividend Amount": 0,
        "Upcoming Dividend Date": "",
        "Url": "https://groww.in/stocks/oracle-financial-services-software-ltd"
    },
    {
        "Book Value": 148.57,
        "Credit Dividend": 3.01,
        "Current Price": 268.4,
        "Day Returns": 0.39,
        "Debt to Equity": 0.11,
        "Dividend Yield": 1.12,
        "EPS(TTM)": 26.08,
        "Face Value": 10.0,
        "Industry P/E": 18.63,
        "Market Cap": 40095.0,
        "Name": "Petronet LNG",
        "P/B Ratio": 1.8,
        "P/E Ratio(TTM)": 10.25,
        "Qty": 5,
        "ROE": 17.56,
        "Stock Average Value": 280.07,
        "Time": "2026-06-09 15:33:54",
        "To Be Credit Dividend": 15.05,
        "Total Returns": -58.35000000000008,
        "Upcoming Dividend Amount": 3.0,
        "Upcoming Dividend Date": "12 Jun, 2026",
        "Url": "https://groww.in/stocks/petronet-lng-ltd"
    },
    {
        "Book Value": 918.71,
        "Credit Dividend": 75.96,
        "Current Price": 4576.0,
        "Day Returns": 1.06,
        "Debt to Equity": 0.02,
        "Dividend Yield": 1.66,
        "EPS(TTM)": 157.92,
        "Face Value": 10.0,
        "Industry P/E": 44.77,
        "Market Cap": 20729.0,
        "Name": "Pfizer",
        "P/B Ratio": 4.93,
        "P/E Ratio(TTM)": 28.69,
        "Qty": 4,
        "ROE": 17.19,
        "Stock Average Value": 5084.28,
        "Time": "2026-06-09 15:34:01",
        "To Be Credit Dividend": 303.84,
        "Total Returns": -2033.119999999999,
        "Upcoming Dividend Amount": 75.0,
        "Upcoming Dividend Date": "17 Jul, 2026",
        "Url": "https://groww.in/stocks/pfizer-ltd"
    },
    {
        "Book Value": 78.11,
        "Credit Dividend": 11.0,
        "Current Price": 236.05,
        "Day Returns": -0.0,
        "Debt to Equity": 0.11,
        "Dividend Yield": 4.66,
        "EPS(TTM)": 14.88,
        "Face Value": 10.0,
        "Industry P/E": 24.57,
        "Market Cap": 3525.0,
        "Name": "Quess Corp",
        "P/B Ratio": 3.02,
        "P/E Ratio(TTM)": 15.86,
        "Qty": 70,
        "ROE": 19.0,
        "Stock Average Value": 212.85,
        "Time": "2026-06-09 15:34:08",
        "To Be Credit Dividend": 770.0,
        "Total Returns": 1624.0000000000011,
        "Upcoming Dividend Amount": 0,
        "Upcoming Dividend Date": "",
        "Url": "https://groww.in/stocks/quess-corp-ltd"
    },
    {
        "Book Value": 234.07,
        "Credit Dividend": 110.18,
        "Current Price": 2152.0,
        "Day Returns": 0.03,
        "Debt to Equity": 0.11,
        "Dividend Yield": 5.12,
        "EPS(TTM)": 135.7,
        "Face Value": 1.0,
        "Industry P/E": 21.2,
        "Market Cap": 778413.0,
        "Name": "Tata Consultancy Services",
        "P/B Ratio": 9.19,
        "P/E Ratio(TTM)": 15.85,
        "Qty": 13,
        "ROE": 57.98,
        "Stock Average Value": 2706.23,
        "Time": "2026-06-09 15:34:14",
        "To Be Credit Dividend": 1432.34,
        "Total Returns": -7204.99,
        "Upcoming Dividend Amount": 0,
        "Upcoming Dividend Date": "",
        "Url": "https://groww.in/stocks/tata-consultancy-services-ltd"
    },
    {
        "Book Value": 302.69,
        "Credit Dividend": 45.64,
        "Current Price": 1486.5,
        "Day Returns": -1.12,
        "Debt to Equity": 0.07,
        "Dividend Yield": 3.07,
        "EPS(TTM)": 49.04,
        "Face Value": 5.0,
        "Industry P/E": 19.05,
        "Market Cap": 147263.0,
        "Name": "Tech Mahindra",
        "P/B Ratio": 4.96,
        "P/E Ratio(TTM)": 30.64,
        "Qty": 9,
        "ROE": 16.24,
        "Stock Average Value": 1522.97,
        "Time": "2026-06-09 15:34:21",
        "To Be Credit Dividend": 410.76,
        "Total Returns": -328.23000000000025,
        "Upcoming Dividend Amount": 36.0,
        "Upcoming Dividend Date": "03 Jul, 2026",
        "Url": "https://groww.in/stocks/tech-mahindra-ltd"
    },
    {
        "Book Value": 167.66,
        "Credit Dividend": 5.14,
        "Current Price": 170.28,
        "Day Returns": 3.09,
        "Debt to Equity": 0,
        "Dividend Yield": 3.02,
        "EPS(TTM)": 25.45,
        "Face Value": 10.0,
        "Industry P/E": 12.49,
        "Market Cap": 126184.0,
        "Name": "Union Bank of India",
        "P/B Ratio": 0.99,
        "P/E Ratio(TTM)": 6.5,
        "Qty": 36,
        "ROE": 15.18,
        "Stock Average Value": 157.9,
        "Time": "2026-06-09 15:34:26",
        "To Be Credit Dividend": 185.04,
        "Total Returns": 445.67999999999984,
        "Upcoming Dividend Amount": 5.0,
        "Upcoming Dividend Date": "03 Jul, 2026",
        "Url": "https://groww.in/stocks/union-bank-of-india"
    },
    {
        "Book Value": 83.85,
        "Credit Dividend": 11.0,
        "Current Price": 181.9,
        "Day Returns": 0.08,
        "Debt to Equity": 0.23,
        "Dividend Yield": 6.05,
        "EPS(TTM)": 12.64,
        "Face Value": 2.0,
        "Industry P/E": 19.05,
        "Market Cap": 190836.0,
        "Name": "Wipro",
        "P/B Ratio": 2.17,
        "P/E Ratio(TTM)": 14.38,
        "Qty": 19,
        "ROE": 14.99,
        "Stock Average Value": 233.44,
        "Time": "2026-06-09 15:34:32",
        "To Be Credit Dividend": 209.0,
        "Total Returns": -979.2599999999999,
        "Upcoming Dividend Amount": 0,
        "Upcoming Dividend Date": "",
        "Url": "https://groww.in/stocks/wipro-ltd"
    }
]