[
    {
        "Book Value": 35.11,
        "Credit Dividend": 4.93,
        "Current Price": 230.15,
        "Day Returns": -0.49,
        "Debt to Equity": 4.3,
        "Dividend Yield": 2.14,
        "EPS(TTM)": 9.64,
        "Face Value": 1.0,
        "Industry P/E": 21.02,
        "Market Cap": 67907.0,
        "Name": "Ashok Leyland",
        "P/B Ratio": 6.59,
        "P/E Ratio(TTM)": 23.99,
        "Qty": 10,
        "ROE": 25.49,
        "Stock Average Value": 224.41,
        "Time": "2025-05-13 15:31:05",
        "To Be Credit Dividend": 49.3,
        "Total Returns": 57.40000000000009,
        "Upcoming Dividend Amount": 0,
        "Upcoming Dividend Date": "",
        "Url": "https://groww.in/stocks/ashok-leyland-ltd"
    },
    {
        "Book Value": 283.29,
        "Credit Dividend": 8.59,
        "Current Price": 232.75,
        "Day Returns": 2.6,
        "Debt to Equity": 0,
        "Dividend Yield": 3.69,
        "EPS(TTM)": 40.06,
        "Face Value": 2.0,
        "Industry P/E": 12.81,
        "Market Cap": 117312.0,
        "Name": "Bank of Baroda",
        "P/B Ratio": 0.8,
        "P/E Ratio(TTM)": 5.66,
        "Qty": 38,
        "ROE": 14.14,
        "Stock Average Value": 246.44,
        "Time": "2025-05-13 15:31:09",
        "To Be Credit Dividend": 326.42,
        "Total Returns": -520.2199999999999,
        "Upcoming Dividend Amount": 0,
        "Upcoming Dividend Date": "",
        "Url": "https://groww.in/stocks/bank-of-baroda"
    },
    {
        "Book Value": 162.21,
        "Credit Dividend": 4.14,
        "Current Price": 112.49,
        "Day Returns": 2.18,
        "Debt to Equity": 0,
        "Dividend Yield": 3.68,
        "EPS(TTM)": 20.97,
        "Face Value": 10.0,
        "Industry P/E": 12.81,
        "Market Cap": 50102.0,
        "Name": "Bank of India",
        "P/B Ratio": 0.68,
        "P/E Ratio(TTM)": 5.25,
        "Qty": 19,
        "ROE": 12.93,
        "Stock Average Value": 114.32,
        "Time": "2025-05-13 15:31:13",
        "To Be Credit Dividend": 78.66,
        "Total Returns": -34.76999999999997,
        "Upcoming Dividend Amount": 0,
        "Upcoming Dividend Date": "",
        "Url": "https://groww.in/stocks/bank-of-india"
    },
    {
        "Book Value": 187.74,
        "Credit Dividend": 9.79,
        "Current Price": 307.05,
        "Day Returns": -0.65,
        "Debt to Equity": 0.75,
        "Dividend Yield": 3.19,
        "EPS(TTM)": 30.74,
        "Face Value": 10.0,
        "Industry P/E": 22.58,
        "Market Cap": 134016.0,
        "Name": "Bharat Petroleum Corporation",
        "P/B Ratio": 1.65,
        "P/E Ratio(TTM)": 10.05,
        "Qty": 36,
        "ROE": 16.39,
        "Stock Average Value": 320.17,
        "Time": "2025-05-13 15:31:17",
        "To Be Credit Dividend": 352.44,
        "Total Returns": -472.32000000000016,
        "Upcoming Dividend Amount": 0,
        "Upcoming Dividend Date": "",
        "Url": "https://groww.in/stocks/bharat-petroleum-corporation-ltd"
    },
    {
        "Book Value": 106.16,
        "Credit Dividend": 4.16,
        "Current Price": 104.78,
        "Day Returns": 3.89,
        "Debt to Equity": 0,
        "Dividend Yield": 3.97,
        "EPS(TTM)": 19.34,
        "Face Value": 2.0,
        "Industry P/E": 12.81,
        "Market Cap": 91441.0,
        "Name": "Canara Bank",
        "P/B Ratio": 0.95,
        "P/E Ratio(TTM)": 5.21,
        "Qty": 40,
        "ROE": 18.21,
        "Stock Average Value": 103.94,
        "Time": "2025-05-13 15:31:20",
        "To Be Credit Dividend": 166.4,
        "Total Returns": 33.600000000000136,
        "Upcoming Dividend Amount": 0,
        "Upcoming Dividend Date": "",
        "Url": "https://groww.in/stocks/canara-bank"
    },
    {
        "Book Value": 23.03,
        "Credit Dividend": 13.04,
        "Current Price": 205.1,
        "Day Returns": 0.4,
        "Debt to Equity": 0.04,
        "Dividend Yield": 6.36,
        "EPS(TTM)": 9.55,
        "Face Value": 5.0,
        "Industry P/E": 46.93,
        "Market Cap": 20213.0,
        "Name": "Castrol India",
        "P/B Ratio": 8.87,
        "P/E Ratio(TTM)": 21.4,
        "Qty": 67,
        "ROE": 40.7,
        "Stock Average Value": 223.87,
        "Time": "2025-05-13 15:31:24",
        "To Be Credit Dividend": 873.68,
        "Total Returns": -1257.5900000000006,
        "Upcoming Dividend Amount": 0,
        "Upcoming Dividend Date": "",
        "Url": "https://groww.in/stocks/castrol-india-ltd"
    },
    {
        "Book Value": 160.81,
        "Credit Dividend": 26.52,
        "Current Price": 395.8,
        "Day Returns": 0.076,
        "Debt to Equity": 0.09,
        "Dividend Yield": 6.7,
        "EPS(TTM)": 57.37,
        "Face Value": 10.0,
        "Industry P/E": 9.17,
        "Market Cap": 243705.0,
        "Name": "Coal India",
        "P/B Ratio": 2.46,
        "P/E Ratio(TTM)": 6.89,
        "Qty": 50,
        "ROE": 35.68,
        "Stock Average Value": 374.22,
        "Time": "2025-05-13 15:31:28",
        "To Be Credit Dividend": 1326.0,
        "Total Returns": 1078.999999999999,
        "Upcoming Dividend Amount": 0,
        "Upcoming Dividend Date": "",
        "Url": "https://groww.in/stocks/coal-india-ltd"
    },
    {
        "Book Value": 60.77,
        "Credit Dividend": 57.72,
        "Current Price": 2599.9,
        "Day Returns": -0.45,
        "Debt to Equity": 0.04,
        "Dividend Yield": 2.22,
        "EPS(TTM)": 53.74,
        "Face Value": 1.0,
        "Industry P/E": 55.07,
        "Market Cap": 71009.0,
        "Name": "Colgate-Palmolive (India)",
        "P/B Ratio": 42.96,
        "P/E Ratio(TTM)": 48.58,
        "Qty": 1,
        "ROE": 88.88,
        "Stock Average Value": 2701.95,
        "Time": "2025-05-13 15:31:32",
        "To Be Credit Dividend": 57.72,
        "Total Returns": -102.04999999999973,
        "Upcoming Dividend Amount": 0,
        "Upcoming Dividend Date": "",
        "Url": "https://groww.in/stocks/colgatepalmolive-india-ltd"
    },
    {
        "Book Value": 127.46,
        "Credit Dividend": 5.37,
        "Current Price": 183.4,
        "Day Returns": -2.34,
        "Debt to Equity": 0.23,
        "Dividend Yield": 2.93,
        "EPS(TTM)": 18.9,
        "Face Value": 10.0,
        "Industry P/E": 16.03,
        "Market Cap": 123480.0,
        "Name": "GAIL (India)",
        "P/B Ratio": 1.47,
        "P/E Ratio(TTM)": 9.94,
        "Qty": 31,
        "ROE": 13.77,
        "Stock Average Value": 212.09,
        "Time": "2025-05-13 15:31:35",
        "To Be Credit Dividend": 166.47,
        "Total Returns": -889.3899999999999,
        "Upcoming Dividend Amount": 0,
        "Upcoming Dividend Date": "",
        "Url": "https://groww.in/stocks/gail-india-ltd"
    },
    {
        "Book Value": 339.61,
        "Credit Dividend": 10.08,
        "Current Price": 416.6,
        "Day Returns": 0.64,
        "Debt to Equity": 0.0,
        "Dividend Yield": 2.42,
        "EPS(TTM)": 42.83,
        "Face Value": 5.0,
        "Industry P/E": 15.23,
        "Market Cap": 72606.0,
        "Name": "General Insurance",
        "P/B Ratio": 1.22,
        "P/E Ratio(TTM)": 9.66,
        "Qty": 51,
        "ROE": 12.61,
        "Stock Average Value": 405.37,
        "Time": "2025-05-13 15:31:39",
        "To Be Credit Dividend": 514.08,
        "Total Returns": 572.7300000000009,
        "Upcoming Dividend Amount": 0,
        "Upcoming Dividend Date": "",
        "Url": "https://groww.in/stocks/general-insurance-corporation-of-india-ltd"
    },
    {
        "Book Value": 256.68,
        "Credit Dividend": 58.32,
        "Current Price": 1619.9,
        "Day Returns": -3.02,
        "Debt to Equity": 0.09,
        "Dividend Yield": 3.6,
        "EPS(TTM)": 64.12,
        "Face Value": 2.0,
        "Industry P/E": 26.7,
        "Market Cap": 453087.0,
        "Name": "HCL Technologies",
        "P/B Ratio": 6.5,
        "P/E Ratio(TTM)": 26.04,
        "Qty": 28,
        "ROE": 24.98,
        "Stock Average Value": 1397.61,
        "Time": "2025-05-13 15:31:43",
        "To Be Credit Dividend": 1632.96,
        "Total Returns": 6224.120000000005,
        "Upcoming Dividend Amount": 0,
        "Upcoming Dividend Date": "",
        "Url": "https://groww.in/stocks/hcl-technologies-ltd"
    },
    {
        "Book Value": 380.15,
        "Credit Dividend": 89.58,
        "Current Price": 4501.4,
        "Day Returns": -0.61,
        "Debt to Equity": 0.0,
        "Dividend Yield": 1.99,
        "EPS(TTM)": 115.04,
        "Face Value": 5.0,
        "Industry P/E": 18.56,
        "Market Cap": 96813.0,
        "Name": "HDFC Asset Management Company",
        "P/B Ratio": 11.91,
        "P/E Ratio(TTM)": 39.35,
        "Qty": 2,
        "ROE": 30.26,
        "Stock Average Value": 4361.73,
        "Time": "2025-05-13 15:31:47",
        "To Be Credit Dividend": 179.16,
        "Total Returns": 279.34000000000015,
        "Upcoming Dividend Amount": 0,
        "Upcoming Dividend Date": "",
        "Url": "https://groww.in/stocks/hdfc-asset-management-company-ltd"
    },
    {
        "Book Value": 950.47,
        "Credit Dividend": 142.35,
        "Current Price": 4055.5,
        "Day Returns": 1.77,
        "Debt to Equity": 0.03,
        "Dividend Yield": 3.51,
        "EPS(TTM)": 207.6,
        "Face Value": 2.0,
        "Industry P/E": 21.02,
        "Market Cap": 79815.0,
        "Name": "Hero MotoCorp",
        "P/B Ratio": 4.2,
        "P/E Ratio(TTM)": 19.22,
        "Qty": 34,
        "ROE": 21.77,
        "Stock Average Value": 4081.06,
        "Time": "2025-05-13 15:31:50",
        "To Be Credit Dividend": 4839.9,
        "Total Returns": -869.0399999999981,
        "Upcoming Dividend Amount": 0,
        "Upcoming Dividend Date": "",
        "Url": "https://groww.in/stocks/hero-motocorp-ltd"
    },
    {
        "Book Value": 31.54,
        "Credit Dividend": 28.65,
        "Current Price": 429.5,
        "Day Returns": -1.25,
        "Debt to Equity": 0.82,
        "Dividend Yield": 6.67,
        "EPS(TTM)": 24.5,
        "Face Value": 2.0,
        "Industry P/E": 12.88,
        "Market Cap": 183780.0,
        "Name": "Hindustan Zinc",
        "P/B Ratio": 13.79,
        "P/E Ratio(TTM)": 17.75,
        "Qty": 45,
        "ROE": 77.69,
        "Stock Average Value": 516.43,
        "Time": "2025-05-13 15:31:54",
        "To Be Credit Dividend": 1289.25,
        "Total Returns": -3911.8499999999976,
        "Upcoming Dividend Amount": 0,
        "Upcoming Dividend Date": "",
        "Url": "https://groww.in/stocks/hindustan-zinc-ltd"
    },
    {
        "Book Value": 240.36,
        "Credit Dividend": 10.52,
        "Current Price": 389.6,
        "Day Returns": 0.21,
        "Debt to Equity": 1.38,
        "Dividend Yield": 2.7,
        "EPS(TTM)": 31.66,
        "Face Value": 10.0,
        "Industry P/E": 22.58,
        "Market Cap": 82857.0,
        "Name": "HPCL",
        "P/B Ratio": 1.62,
        "P/E Ratio(TTM)": 12.3,
        "Qty": 36,
        "ROE": 13.17,
        "Stock Average Value": 373.95,
        "Time": "2025-05-13 15:31:58",
        "To Be Credit Dividend": 378.72,
        "Total Returns": 563.4000000000012,
        "Upcoming Dividend Amount": 0,
        "Upcoming Dividend Date": "",
        "Url": "https://groww.in/stocks/hindustan-petroleum-corporation-ltd"
    },
    {
        "Book Value": 210.26,
        "Credit Dividend": 52.39,
        "Current Price": 2359.7,
        "Day Returns": -0.96,
        "Debt to Equity": 0.03,
        "Dividend Yield": 2.22,
        "EPS(TTM)": 45.32,
        "Face Value": 1.0,
        "Industry P/E": 51.66,
        "Market Cap": 559896.0,
        "Name": "Hindustan Unilever",
        "P/B Ratio": 11.33,
        "P/E Ratio(TTM)": 52.58,
        "Qty": 0,
        "ROE": 21.56,
        "Stock Average Value": 0,
        "Time": "2025-05-13 15:32:02",
        "To Be Credit Dividend": 0.0,
        "Total Returns": 0.0,
        "Upcoming Dividend Amount": 0,
        "Upcoming Dividend Date": "",
        "Url": "https://groww.in/stocks/hindustan-unilever-ltd"
    },
    {
        "Book Value": 75.83,
        "Credit Dividend": 10.88,
        "Current Price": 203.01,
        "Day Returns": -1.11,
        "Debt to Equity": 0.01,
        "Dividend Yield": 5.36,
        "EPS(TTM)": 12.27,
        "Face Value": 2.0,
        "Industry P/E": 16.03,
        "Market Cap": 28728.0,
        "Name": "Indraprastha Gas",
        "P/B Ratio": 2.71,
        "P/E Ratio(TTM)": 16.72,
        "Qty": 17,
        "ROE": 16.18,
        "Stock Average Value": 194.22,
        "Time": "2025-05-13 15:32:05",
        "To Be Credit Dividend": 184.96,
        "Total Returns": 149.42999999999986,
        "Upcoming Dividend Amount": 0,
        "Upcoming Dividend Date": "",
        "Url": "https://groww.in/stocks/indraprastha-gas-ltd"
    },
    {
        "Book Value": 210.73,
        "Credit Dividend": 41.39,
        "Current Price": 1567.9,
        "Day Returns": -3.63,
        "Debt to Equity": 0.09,
        "Dividend Yield": 2.64,
        "EPS(TTM)": 64.32,
        "Face Value": 5.0,
        "Industry P/E": 26.7,
        "Market Cap": 675611.0,
        "Name": "Infosys",
        "P/B Ratio": 7.72,
        "P/E Ratio(TTM)": 25.29,
        "Qty": 31,
        "ROE": 27.88,
        "Stock Average Value": 1644.0,
        "Time": "2025-05-13 15:32:09",
        "To Be Credit Dividend": 1283.09,
        "Total Returns": -2359.099999999997,
        "Upcoming Dividend Amount": 22.0,
        "Upcoming Dividend Date": "30 May, 2025",
        "Url": "https://groww.in/stocks/infosys-ltd"
    },
    {
        "Book Value": 132.31,
        "Credit Dividend": 2.99,
        "Current Price": 141.77,
        "Day Returns": -0.41,
        "Debt to Equity": 0.82,
        "Dividend Yield": 2.11,
        "EPS(TTM)": 9.63,
        "Face Value": 10.0,
        "Industry P/E": 22.58,
        "Market Cap": 201016.0,
        "Name": "Indian Oil Corporation",
        "P/B Ratio": 1.08,
        "P/E Ratio(TTM)": 14.78,
        "Qty": 23,
        "ROE": 6.5,
        "Stock Average Value": 161.32,
        "Time": "2025-05-13 15:32:13",
        "To Be Credit Dividend": 68.77,
        "Total Returns": -449.64999999999964,
        "Upcoming Dividend Amount": 0,
        "Upcoming Dividend Date": "",
        "Url": "https://groww.in/stocks/indian-oil-corporation-ltd"
    },
    {
        "Book Value": 60.15,
        "Credit Dividend": 13.48,
        "Current Price": 427.9,
        "Day Returns": -1.75,
        "Debt to Equity": 0.0,
        "Dividend Yield": 3.15,
        "EPS(TTM)": 16.09,
        "Face Value": 1.0,
        "Industry P/E": 27.39,
        "Market Cap": 544990.0,
        "Name": "ITC",
        "P/B Ratio": 7.24,
        "P/E Ratio(TTM)": 27.07,
        "Qty": 37,
        "ROE": 27.29,
        "Stock Average Value": 403.21,
        "Time": "2025-05-13 15:32:16",
        "To Be Credit Dividend": 498.76,
        "Total Returns": 913.53,
        "Upcoming Dividend Amount": 0,
        "Upcoming Dividend Date": "",
        "Url": "https://groww.in/stocks/itc-ltd"
    },
    {
        "Book Value": 595.29,
        "Credit Dividend": 29.65,
        "Current Price": 1392.2,
        "Day Returns": -1.21,
        "Debt to Equity": 0.03,
        "Dividend Yield": 2.13,
        "EPS(TTM)": 105.34,
        "Face Value": 10.0,
        "Industry P/E": 16.03,
        "Market Cap": 13909.0,
        "Name": "Mahanagar Gas",
        "P/B Ratio": 2.37,
        "P/E Ratio(TTM)": 13.37,
        "Qty": 8,
        "ROE": 17.7,
        "Stock Average Value": 1274.6,
        "Time": "2025-05-13 15:32:20",
        "To Be Credit Dividend": 237.2,
        "Total Returns": 940.8000000000011,
        "Upcoming Dividend Amount": 0,
        "Upcoming Dividend Date": "",
        "Url": "https://groww.in/stocks/mahanagar-gas-ltd"
    },
    {
        "Book Value": 506.17,
        "Credit Dividend": 56.14,
        "Current Price": 2494.9,
        "Day Returns": -1.48,
        "Debt to Equity": 0.2,
        "Dividend Yield": 2.25,
        "EPS(TTM)": 89.48,
        "Face Value": 10.0,
        "Industry P/E": 26.7,
        "Market Cap": 48159.0,
        "Name": "Mphasis",
        "P/B Ratio": 5.0,
        "P/E Ratio(TTM)": 28.29,
        "Qty": 4,
        "ROE": 17.68,
        "Stock Average Value": 2440.9,
        "Time": "2025-05-13 15:32:24",
        "To Be Credit Dividend": 224.56,
        "Total Returns": 216.0,
        "Upcoming Dividend Amount": 0,
        "Upcoming Dividend Date": "",
        "Url": "https://groww.in/stocks/mphasis-ltd"
    },
    {
        "Book Value": 174.25,
        "Credit Dividend": 6.5,
        "Current Price": 256.95,
        "Day Returns": 0.039,
        "Debt to Equity": 5.53,
        "Dividend Yield": 2.53,
        "EPS(TTM)": 18.31,
        "Face Value": 2.0,
        "Industry P/E": 18.56,
        "Market Cap": 31742.0,
        "Name": "Mahindra Financial",
        "P/B Ratio": 1.47,
        "P/E Ratio(TTM)": 14.03,
        "Qty": 4,
        "ROE": 10.51,
        "Stock Average Value": 262.9,
        "Time": "2025-05-13 15:32:28",
        "To Be Credit Dividend": 26.0,
        "Total Returns": -23.799999999999955,
        "Upcoming Dividend Amount": 0,
        "Upcoming Dividend Date": "",
        "Url": "https://groww.in/stocks/mahindra-mahindra-financial-services-ltd"
    },
    {
        "Book Value": 85.17,
        "Credit Dividend": 4.9,
        "Current Price": 165.4,
        "Day Returns": -2.1,
        "Debt to Equity": 0.01,
        "Dividend Yield": 2.96,
        "EPS(TTM)": 22.85,
        "Face Value": 5.0,
        "Industry P/E": 12.88,
        "Market Cap": 31030.0,
        "Name": "National Aluminium Co",
        "P/B Ratio": 1.98,
        "P/E Ratio(TTM)": 7.39,
        "Qty": 41,
        "ROE": 17.81,
        "Stock Average Value": 177.13,
        "Time": "2025-05-13 15:32:31",
        "To Be Credit Dividend": 200.9,
        "Total Returns": -480.9299999999996,
        "Upcoming Dividend Amount": 0,
        "Upcoming Dividend Date": "",
        "Url": "https://groww.in/stocks/national-aluminium-company-ltd"
    },
    {
        "Book Value": 66.38,
        "Credit Dividend": 19.12,
        "Current Price": 713.6,
        "Day Returns": 6.14,
        "Debt to Equity": 0.02,
        "Dividend Yield": 2.68,
        "EPS(TTM)": 20.27,
        "Face Value": 10.0,
        "Industry P/E": 18.56,
        "Market Cap": 42696.0,
        "Name": "Nippon Life India AMC",
        "P/B Ratio": 10.13,
        "P/E Ratio(TTM)": 33.19,
        "Qty": 58,
        "ROE": 30.53,
        "Stock Average Value": 581.93,
        "Time": "2025-05-13 15:32:35",
        "To Be Credit Dividend": 1108.96,
        "Total Returns": 7636.860000000004,
        "Upcoming Dividend Amount": 0,
        "Upcoming Dividend Date": "",
        "Url": "https://groww.in/stocks/reliance-nippon-life-asset-management-ltd"
    },
    {
        "Book Value": 32.27,
        "Credit Dividend": 2.39,
        "Current Price": 67.3,
        "Day Returns": -1.15,
        "Debt to Equity": 0.15,
        "Dividend Yield": 3.55,
        "EPS(TTM)": 7.37,
        "Face Value": 1.0,
        "Industry P/E": 9.17,
        "Market Cap": 59820.0,
        "Name": "NMDC",
        "P/B Ratio": 2.11,
        "P/E Ratio(TTM)": 9.23,
        "Qty": 211,
        "ROE": 21.43,
        "Stock Average Value": 66.32,
        "Time": "2025-05-13 15:32:39",
        "To Be Credit Dividend": 504.29,
        "Total Returns": 206.78000000000083,
        "Upcoming Dividend Amount": 0,
        "Upcoming Dividend Date": "",
        "Url": "https://groww.in/stocks/nmdc-ltd"
    },
    {
        "Book Value": 173.54,
        "Credit Dividend": 7.6,
        "Current Price": 342.3,
        "Day Returns": -1.79,
        "Debt to Equity": 1.44,
        "Dividend Yield": 2.22,
        "EPS(TTM)": 22.67,
        "Face Value": 10.0,
        "Industry P/E": 22.11,
        "Market Cap": 338123.0,
        "Name": "NTPC",
        "P/B Ratio": 2.01,
        "P/E Ratio(TTM)": 15.38,
        "Qty": 3,
        "ROE": 13.12,
        "Stock Average Value": 330.65,
        "Time": "2025-05-13 15:32:43",
        "To Be Credit Dividend": 22.8,
        "Total Returns": 34.9500000000001,
        "Upcoming Dividend Amount": 0,
        "Upcoming Dividend Date": "",
        "Url": "https://groww.in/stocks/ntpc-ltd"
    },
    {
        "Book Value": 323.84,
        "Credit Dividend": 9.47,
        "Current Price": 408.2,
        "Day Returns": -1.98,
        "Debt to Equity": 0.53,
        "Dividend Yield": 2.32,
        "EPS(TTM)": 45.38,
        "Face Value": 10.0,
        "Industry P/E": 7.64,
        "Market Cap": 67724.0,
        "Name": "Oil India",
        "P/B Ratio": 1.29,
        "P/E Ratio(TTM)": 9.17,
        "Qty": 10,
        "ROE": 15.93,
        "Stock Average Value": 360.02,
        "Time": "2025-05-13 15:32:46",
        "To Be Credit Dividend": 94.7,
        "Total Returns": 481.80000000000007,
        "Upcoming Dividend Amount": 0,
        "Upcoming Dividend Date": "",
        "Url": "https://groww.in/stocks/oil-india-ltd"
    },
    {
        "Book Value": 280.02,
        "Credit Dividend": 12.1,
        "Current Price": 241.0,
        "Day Returns": -1.24,
        "Debt to Equity": 0.54,
        "Dividend Yield": 5.02,
        "EPS(TTM)": 31.01,
        "Face Value": 5.0,
        "Industry P/E": 7.64,
        "Market Cap": 306959.0,
        "Name": "Oil & Natural Gas Corporation",
        "P/B Ratio": 0.87,
        "P/E Ratio(TTM)": 7.87,
        "Qty": 48,
        "ROE": 11.66,
        "Stock Average Value": 262.55,
        "Time": "2025-05-13 15:32:51",
        "To Be Credit Dividend": 580.8,
        "Total Returns": -1034.4000000000005,
        "Upcoming Dividend Amount": 0,
        "Upcoming Dividend Date": "",
        "Url": "https://groww.in/stocks/oil-natural-gas-corporation-ltd"
    },
    {
        "Book Value": 962.36,
        "Credit Dividend": 257.82,
        "Current Price": 8481.0,
        "Day Returns": -2.67,
        "Debt to Equity": 0.01,
        "Dividend Yield": 3.04,
        "EPS(TTM)": 273.85,
        "Face Value": 5.0,
        "Industry P/E": 26.7,
        "Market Cap": 75729.0,
        "Name": "Oracle Finl. Service",
        "P/B Ratio": 9.06,
        "P/E Ratio(TTM)": 31.82,
        "Qty": 4,
        "ROE": 28.46,
        "Stock Average Value": 7947.07,
        "Time": "2025-05-13 15:32:54",
        "To Be Credit Dividend": 1031.28,
        "Total Returns": 2135.720000000001,
        "Upcoming Dividend Amount": 0,
        "Upcoming Dividend Date": "",
        "Url": "https://groww.in/stocks/oracle-financial-services-software-ltd"
    },
    {
        "Book Value": 126.19,
        "Credit Dividend": 9.92,
        "Current Price": 312.0,
        "Day Returns": -0.73,
        "Debt to Equity": 0.15,
        "Dividend Yield": 3.18,
        "EPS(TTM)": 24.28,
        "Face Value": 10.0,
        "Industry P/E": 16.03,
        "Market Cap": 47145.0,
        "Name": "Petronet LNG",
        "P/B Ratio": 2.49,
        "P/E Ratio(TTM)": 12.94,
        "Qty": 17,
        "ROE": 20.89,
        "Stock Average Value": 309.74,
        "Time": "2025-05-13 15:32:58",
        "To Be Credit Dividend": 168.64,
        "Total Returns": 38.419999999999845,
        "Upcoming Dividend Amount": 0,
        "Upcoming Dividend Date": "",
        "Url": "https://groww.in/stocks/petronet-lng-ltd"
    },
    {
        "Book Value": 333.46,
        "Credit Dividend": 13.44,
        "Current Price": 412.4,
        "Day Returns": -0.37,
        "Debt to Equity": 8.27,
        "Dividend Yield": 3.26,
        "EPS(TTM)": 67.57,
        "Face Value": 10.0,
        "Industry P/E": 18.56,
        "Market Cap": 136575.0,
        "Name": "Power Finance Corporation",
        "P/B Ratio": 1.24,
        "P/E Ratio(TTM)": 6.12,
        "Qty": 79,
        "ROE": 19.26,
        "Stock Average Value": 448.01,
        "Time": "2025-05-13 15:33:02",
        "To Be Credit Dividend": 1061.76,
        "Total Returns": -2813.190000000001,
        "Upcoming Dividend Amount": 0,
        "Upcoming Dividend Date": "",
        "Url": "https://groww.in/stocks/power-finance-corporation-ltd"
    },
    {
        "Book Value": 297.64,
        "Credit Dividend": 17.54,
        "Current Price": 402.2,
        "Day Returns": -2.53,
        "Debt to Equity": 6.33,
        "Dividend Yield": 4.36,
        "EPS(TTM)": 60.32,
        "Face Value": 10.0,
        "Industry P/E": 18.56,
        "Market Cap": 108686.0,
        "Name": "REC Limited",
        "P/B Ratio": 1.39,
        "P/E Ratio(TTM)": 6.84,
        "Qty": 74,
        "ROE": 20.27,
        "Stock Average Value": 498.52,
        "Time": "2025-05-13 15:33:06",
        "To Be Credit Dividend": 1297.96,
        "Total Returns": -7127.679999999999,
        "Upcoming Dividend Amount": 0,
        "Upcoming Dividend Date": "",
        "Url": "https://groww.in/stocks/rec-ltd"
    },
    {
        "Book Value": 514.85,
        "Credit Dividend": 15.88,
        "Current Price": 801.95,
        "Day Returns": 0.037,
        "Debt to Equity": 0,
        "Dividend Yield": 1.98,
        "EPS(TTM)": 86.91,
        "Face Value": 1.0,
        "Industry P/E": 12.81,
        "Market Cap": 715398.0,
        "Name": "State Bank of India",
        "P/B Ratio": 1.56,
        "P/E Ratio(TTM)": 9.22,
        "Qty": 0,
        "ROE": 16.88,
        "Stock Average Value": 0,
        "Time": "2025-05-13 15:33:10",
        "To Be Credit Dividend": 0.0,
        "Total Returns": 0.0,
        "Upcoming Dividend Amount": 15.9,
        "Upcoming Dividend Date": "16 May, 2025",
        "Url": "https://groww.in/stocks/state-bank-of-india"
    },
    {
        "Book Value": 286.93,
        "Credit Dividend": 16.83,
        "Current Price": 620.95,
        "Day Returns": 0.59,
        "Debt to Equity": 0.01,
        "Dividend Yield": 2.71,
        "EPS(TTM)": 44.32,
        "Face Value": 5.0,
        "Industry P/E": 18.14,
        "Market Cap": 24313.0,
        "Name": "Sun TV Network",
        "P/B Ratio": 2.15,
        "P/E Ratio(TTM)": 13.92,
        "Qty": 13,
        "ROE": 16.25,
        "Stock Average Value": 705.55,
        "Time": "2025-05-13 15:33:14",
        "To Be Credit Dividend": 218.79,
        "Total Returns": -1099.7999999999988,
        "Upcoming Dividend Amount": 0,
        "Upcoming Dividend Date": "",
        "Url": "https://groww.in/stocks/sun-tv-network-ltd"
    },
    {
        "Book Value": 260.08,
        "Credit Dividend": 120.67,
        "Current Price": 3518.0,
        "Day Returns": -2.83,
        "Debt to Equity": 0.1,
        "Dividend Yield": 3.43,
        "EPS(TTM)": 134.2,
        "Face Value": 1.0,
        "Industry P/E": 26.7,
        "Market Cap": 1309856.0,
        "Name": "Tata Consultancy Services",
        "P/B Ratio": 13.92,
        "P/E Ratio(TTM)": 26.98,
        "Qty": 0,
        "ROE": 51.24,
        "Stock Average Value": 0,
        "Time": "2025-05-13 15:33:18",
        "To Be Credit Dividend": 0.0,
        "Total Returns": 0.0,
        "Upcoming Dividend Amount": 0,
        "Upcoming Dividend Date": "",
        "Url": "https://groww.in/stocks/tata-consultancy-services-ltd"
    },
    {
        "Book Value": 279.95,
        "Credit Dividend": 40.75,
        "Current Price": 1573.2,
        "Day Returns": 0.0064,
        "Debt to Equity": 0.07,
        "Dividend Yield": 2.59,
        "EPS(TTM)": 43.42,
        "Face Value": 5.0,
        "Industry P/E": 26.7,
        "Market Cap": 153974.0,
        "Name": "Tech Mahindra",
        "P/B Ratio": 5.62,
        "P/E Ratio(TTM)": 36.22,
        "Qty": 8,
        "ROE": 15.54,
        "Stock Average Value": 1703.39,
        "Time": "2025-05-13 15:33:21",
        "To Be Credit Dividend": 326.0,
        "Total Returns": -1041.5200000000004,
        "Upcoming Dividend Amount": 0,
        "Upcoming Dividend Date": "",
        "Url": "https://groww.in/stocks/tech-mahindra-ltd"
    },
    {
        "Book Value": 141.59,
        "Credit Dividend": 4.84,
        "Current Price": 130.7,
        "Day Returns": 2.02,
        "Debt to Equity": 0,
        "Dividend Yield": 3.7,
        "EPS(TTM)": 23.62,
        "Face Value": 10.0,
        "Industry P/E": 12.81,
        "Market Cap": 97901.0,
        "Name": "Union Bank of India",
        "P/B Ratio": 0.91,
        "P/E Ratio(TTM)": 5.43,
        "Qty": 29,
        "ROE": 16.68,
        "Stock Average Value": 122.46,
        "Time": "2025-05-13 15:33:25",
        "To Be Credit Dividend": 140.36,
        "Total Returns": 238.95999999999987,
        "Upcoming Dividend Amount": 0,
        "Upcoming Dividend Date": "",
        "Url": "https://groww.in/stocks/union-bank-of-india"
    },
    {
        "Book Value": 78.64,
        "Credit Dividend": 5.87,
        "Current Price": 251.8,
        "Day Returns": -2.13,
        "Debt to Equity": 0.23,
        "Dividend Yield": 2.33,
        "EPS(TTM)": 12.54,
        "Face Value": 2.0,
        "Industry P/E": 26.7,
        "Market Cap": 269583.0,
        "Name": "Wipro",
        "P/B Ratio": 3.27,
        "P/E Ratio(TTM)": 20.53,
        "Qty": 6,
        "ROE": 15.95,
        "Stock Average Value": 302.64,
        "Time": "2025-05-13 15:33:29",
        "To Be Credit Dividend": 35.22,
        "Total Returns": -305.03999999999985,
        "Upcoming Dividend Amount": 0,
        "Upcoming Dividend Date": "",
        "Url": "https://groww.in/stocks/wipro-ltd"
    },
    {
        "Book Value": 187.74,
        "Credit Dividend": 9.79,
        "Current Price": 306.75,
        "Day Returns": -0.74,
        "Debt to Equity": 0.75,
        "Dividend Yield": 3.19,
        "EPS(TTM)": 30.74,
        "Face Value": 10.0,
        "Industry P/E": 22.58,
        "Market Cap": 134016.0,
        "Name": "Bharat Petroleum Corporation",
        "P/B Ratio": 1.65,
        "P/E Ratio(TTM)": 10.05,
        "Qty": 3,
        "ROE": 16.39,
        "Stock Average Value": 269.13,
        "Time": "2025-05-13 15:33:33",
        "To Be Credit Dividend": 29.37,
        "Total Returns": 112.86000000000001,
        "Upcoming Dividend Amount": 0,
        "Upcoming Dividend Date": "",
        "Url": "https://groww.in/stocks/bharat-petroleum-corporation-ltd"
    },
    {
        "Book Value": 106.16,
        "Credit Dividend": 4.16,
        "Current Price": 104.78,
        "Day Returns": 3.89,
        "Debt to Equity": 0,
        "Dividend Yield": 3.97,
        "EPS(TTM)": 19.34,
        "Face Value": 2.0,
        "Industry P/E": 12.81,
        "Market Cap": 91441.0,
        "Name": "Canara Bank",
        "P/B Ratio": 0.95,
        "P/E Ratio(TTM)": 5.21,
        "Qty": 4,
        "ROE": 18.21,
        "Stock Average Value": 97.74,
        "Time": "2025-05-13 15:33:37",
        "To Be Credit Dividend": 16.64,
        "Total Returns": 28.160000000000025,
        "Upcoming Dividend Amount": 0,
        "Upcoming Dividend Date": "",
        "Url": "https://groww.in/stocks/canara-bank"
    },
    {
        "Book Value": 160.81,
        "Credit Dividend": 26.52,
        "Current Price": 395.8,
        "Day Returns": 0.076,
        "Debt to Equity": 0.09,
        "Dividend Yield": 6.7,
        "EPS(TTM)": 57.37,
        "Face Value": 10.0,
        "Industry P/E": 9.17,
        "Market Cap": 243705.0,
        "Name": "Coal India",
        "P/B Ratio": 2.46,
        "P/E Ratio(TTM)": 6.89,
        "Qty": 2,
        "ROE": 35.68,
        "Stock Average Value": 391.3,
        "Time": "2025-05-13 15:33:42",
        "To Be Credit Dividend": 53.04,
        "Total Returns": 9.0,
        "Upcoming Dividend Amount": 0,
        "Upcoming Dividend Date": "",
        "Url": "https://groww.in/stocks/coal-india-ltd"
    },
    {
        "Book Value": 31.54,
        "Credit Dividend": 28.65,
        "Current Price": 429.5,
        "Day Returns": -1.25,
        "Debt to Equity": 0.82,
        "Dividend Yield": 6.67,
        "EPS(TTM)": 24.5,
        "Face Value": 2.0,
        "Industry P/E": 12.88,
        "Market Cap": 183780.0,
        "Name": "Hindustan Zinc",
        "P/B Ratio": 13.79,
        "P/E Ratio(TTM)": 17.75,
        "Qty": 4,
        "ROE": 77.69,
        "Stock Average Value": 452.46,
        "Time": "2025-05-13 15:33:45",
        "To Be Credit Dividend": 114.6,
        "Total Returns": -91.83999999999992,
        "Upcoming Dividend Amount": 0,
        "Upcoming Dividend Date": "",
        "Url": "https://groww.in/stocks/hindustan-zinc-ltd"
    },
    {
        "Book Value": 75.83,
        "Credit Dividend": 10.88,
        "Current Price": 203.01,
        "Day Returns": -1.11,
        "Debt to Equity": 0.01,
        "Dividend Yield": 5.36,
        "EPS(TTM)": 12.27,
        "Face Value": 2.0,
        "Industry P/E": 16.03,
        "Market Cap": 28728.0,
        "Name": "Indraprastha Gas",
        "P/B Ratio": 2.71,
        "P/E Ratio(TTM)": 16.72,
        "Qty": 5,
        "ROE": 16.18,
        "Stock Average Value": 193.05,
        "Time": "2025-05-13 15:33:49",
        "To Be Credit Dividend": 54.4,
        "Total Returns": 49.7999999999999,
        "Upcoming Dividend Amount": 0,
        "Upcoming Dividend Date": "",
        "Url": "https://groww.in/stocks/indraprastha-gas-ltd"
    },
    {
        "Book Value": 210.73,
        "Credit Dividend": 41.39,
        "Current Price": 1567.9,
        "Day Returns": -3.63,
        "Debt to Equity": 0.09,
        "Dividend Yield": 2.64,
        "EPS(TTM)": 64.32,
        "Face Value": 5.0,
        "Industry P/E": 26.7,
        "Market Cap": 675611.0,
        "Name": "Infosys",
        "P/B Ratio": 7.72,
        "P/E Ratio(TTM)": 25.29,
        "Qty": 1,
        "ROE": 27.88,
        "Stock Average Value": 1812.25,
        "Time": "2025-05-13 15:33:53",
        "To Be Credit Dividend": 41.39,
        "Total Returns": -244.3499999999999,
        "Upcoming Dividend Amount": 22.0,
        "Upcoming Dividend Date": "30 May, 2025",
        "Url": "https://groww.in/stocks/infosys-ltd"
    },
    {
        "Book Value": 60.15,
        "Credit Dividend": 13.48,
        "Current Price": 427.9,
        "Day Returns": -1.75,
        "Debt to Equity": 0.0,
        "Dividend Yield": 3.15,
        "EPS(TTM)": 16.09,
        "Face Value": 1.0,
        "Industry P/E": 27.39,
        "Market Cap": 544990.0,
        "Name": "ITC",
        "P/B Ratio": 7.24,
        "P/E Ratio(TTM)": 27.07,
        "Qty": 8,
        "ROE": 27.29,
        "Stock Average Value": 424.95,
        "Time": "2025-05-13 15:33:57",
        "To Be Credit Dividend": 107.84,
        "Total Returns": 23.59999999999991,
        "Upcoming Dividend Amount": 0,
        "Upcoming Dividend Date": "",
        "Url": "https://groww.in/stocks/itc-ltd"
    },
    {
        "Book Value": 66.38,
        "Credit Dividend": 19.12,
        "Current Price": 713.6,
        "Day Returns": 6.14,
        "Debt to Equity": 0.02,
        "Dividend Yield": 2.68,
        "EPS(TTM)": 20.27,
        "Face Value": 10.0,
        "Industry P/E": 18.56,
        "Market Cap": 42696.0,
        "Name": "Nippon Life India AMC",
        "P/B Ratio": 10.13,
        "P/E Ratio(TTM)": 33.19,
        "Qty": 5,
        "ROE": 30.53,
        "Stock Average Value": 536.65,
        "Time": "2025-05-13 15:34:01",
        "To Be Credit Dividend": 95.6,
        "Total Returns": 884.7500000000002,
        "Upcoming Dividend Amount": 0,
        "Upcoming Dividend Date": "",
        "Url": "https://groww.in/stocks/reliance-nippon-life-asset-management-ltd"
    },
    {
        "Book Value": 32.27,
        "Credit Dividend": 2.39,
        "Current Price": 67.3,
        "Day Returns": -1.15,
        "Debt to Equity": 0.15,
        "Dividend Yield": 3.55,
        "EPS(TTM)": 7.37,
        "Face Value": 1.0,
        "Industry P/E": 9.17,
        "Market Cap": 59820.0,
        "Name": "NMDC",
        "P/B Ratio": 2.11,
        "P/E Ratio(TTM)": 9.23,
        "Qty": 4,
        "ROE": 21.43,
        "Stock Average Value": 64.71,
        "Time": "2025-05-13 15:34:06",
        "To Be Credit Dividend": 9.56,
        "Total Returns": 10.360000000000014,
        "Upcoming Dividend Amount": 0,
        "Upcoming Dividend Date": "",
        "Url": "https://groww.in/stocks/nmdc-ltd"
    },
    {
        "Book Value": 962.36,
        "Credit Dividend": 257.82,
        "Current Price": 8481.0,
        "Day Returns": -2.67,
        "Debt to Equity": 0.01,
        "Dividend Yield": 3.04,
        "EPS(TTM)": 273.85,
        "Face Value": 5.0,
        "Industry P/E": 26.7,
        "Market Cap": 75729.0,
        "Name": "Oracle Finl. Service",
        "P/B Ratio": 9.06,
        "P/E Ratio(TTM)": 31.82,
        "Qty": 1,
        "ROE": 28.46,
        "Stock Average Value": 9272,
        "Time": "2025-05-13 15:34:09",
        "To Be Credit Dividend": 257.82,
        "Total Returns": -791.0,
        "Upcoming Dividend Amount": 0,
        "Upcoming Dividend Date": "",
        "Url": "https://groww.in/stocks/oracle-financial-services-software-ltd"
    },
    {
        "Book Value": 141.59,
        "Credit Dividend": 4.84,
        "Current Price": 130.7,
        "Day Returns": 2.02,
        "Debt to Equity": 0,
        "Dividend Yield": 3.7,
        "EPS(TTM)": 23.62,
        "Face Value": 10.0,
        "Industry P/E": 12.81,
        "Market Cap": 97901.0,
        "Name": "Union Bank of India",
        "P/B Ratio": 0.91,
        "P/E Ratio(TTM)": 5.43,
        "Qty": 2,
        "ROE": 16.68,
        "Stock Average Value": 112.99,
        "Time": "2025-05-13 15:34:13",
        "To Be Credit Dividend": 9.68,
        "Total Returns": 35.41999999999999,
        "Upcoming Dividend Amount": 0,
        "Upcoming Dividend Date": "",
        "Url": "https://groww.in/stocks/union-bank-of-india"
    }
]